django_raise_response-0.1.0.dist-info/DESCRIPTION.rst
django_raise_response-0.1.0.dist-info/METADATA
django_raise_response-0.1.0.dist-info/RECORD
django_raise_response-0.1.0.dist-info/WHEEL
django_raise_response-0.1.0.dist-info/metadata.json
django_raise_response-0.1.0.dist-info/top_level.txt
raiseresponse/__init__.py
raiseresponse/middlewares.py
raiseresponse/utils.py
