Metadata-Version: 2.0
Name: django-raise-response
Version: 0.1.0
Summary: Raise any response object in Django
Home-page: https://github.com/wearewhys/django-raise-response
Author: Jacopo Cascioli
Author-email: jacopocascioli@gmail.com
License: MIT
Platform: UNKNOWN
Classifier: Development Status :: 4 - Beta
Classifier: License :: OSI Approved :: MIT License
Classifier: Intended Audience :: Developers
Classifier: Operating System :: OS Independent
Classifier: Programming Language :: Python :: 3
Classifier: Framework :: Django
